LICENSE
password_trainer/__init__.py
password_trainer/constants.py
password_trainer/exceptions.py
password_trainer/main.py
password_trainer/trainer.py
password_trainer/utils.py
password_trainer-1.0.0.dist-info/LICENSE
password_trainer-1.0.0.dist-info/METADATA
password_trainer-1.0.0.dist-info/WHEEL
password_trainer-1.0.0.dist-info/entry_points.txt
password_trainer-1.0.0.dist-info/RECORD
