Metadata-Version: 2.1
Name: password-trainer
Version: 1.0.0
Summary: Train user to enter new password
Home-page: https://github.com/hile/password-trainer
License: BSD-3-Clause
Author: Ilkka Tuohela
Author-email: hile@iki.fi
Requires-Python: >=3.10,<4.0
Classifier: Environment :: Console
Classifier: License :: OSI Approved :: BSD License
Classifier: Operating System :: MacOS
Classifier: Operating System :: POSIX
Classifier: Operating System :: Unix
Classifier: Programming Language :: Python :: 3
Classifier: Programming Language :: Python :: 3.10
Classifier: Programming Language :: Python :: 3.11
Classifier: Programming Language :: Python :: 3.12
Classifier: Topic :: Utilities
